emptyspacesampler/ESSampler.py
emptyspacesampler/__init__.py
emptyspacesampler-0.1.dist-info/licenses/LICENSE
emptyspacesampler-0.1.dist-info/METADATA
emptyspacesampler-0.1.dist-info/WHEEL
emptyspacesampler-0.1.dist-info/top_level.txt
emptyspacesampler-0.1.dist-info/RECORD
