Metadata-Version: 2.4
Name: emptyspacesampler
Version: 0.1
Summary: Empty Space Sampler: An advanced Optuna sampler that uses the EmptySpaceSearch library to iteratively find and sample the largest unexplored "gaps" in the search space.
Home-page: https://github.com/mariolpantunes/Optuna_ESA_Sampler
Author: Mário Antunes
Author-email: mario.antunes@ua.pt
Classifier: Programming Language :: Python :: 3
Classifier: License :: OSI Approved :: MIT License
Classifier: Operating System :: OS Independent
Requires-Python: >=3.8
License-File: LICENSE
Requires-Dist: EmptySpaceSearch>=0.1.4
Requires-Dist: optuna>=4.6.0
Dynamic: license-file
